README.rst
cbvpatterns.py
setup.py
django_cbvpatterns.egg-info/PKG-INFO
django_cbvpatterns.egg-info/SOURCES.txt
django_cbvpatterns.egg-info/dependency_links.txt
django_cbvpatterns.egg-info/requires.txt
django_cbvpatterns.egg-info/top_level.txt