Metadata-Version: 1.1
Name: django-cbvpatterns
Version: 0.1
Summary: A better patterns() for classbased views
Home-page: https://github.com/mjtamlyn/django-cbvpatterns
Author: Marc Tamlyn
Author-email: marc.tamlyn@gmail.com
License: BSD
Platform: UNKNOWN
Classifier: Development Status :: 4 - Beta
Classifier: Environment :: Web Environment
Classifier: Framework :: Django
Classifier: Intended Audience :: Developers
Classifier: License :: OSI Approved :: BSD License
Classifier: Natural Language :: English
Classifier: Programming Language :: Python
Classifier: Programming Language :: Python :: 2.6
Classifier: Programming Language :: Python :: 2.7
Classifier: Programming Language :: Python :: 3.2
Classifier: Programming Language :: Python :: 3.3
